{
  "status": "MAX ITER (50)",
  "iterations": 50,
  "gap": 8.119463676275373,
  "alpha": 12800.0,
  "total_elapsed_seconds": 1046.2223028317094,
  "start_utc": "2026-03-16T15:12:12.289509+00:00",
  "end_utc": "2026-03-16T15:29:38.511805+00:00",
  "time_str": "2025-10-09 21:00:00+00:00",
  "n_total": 5,
  "n_per_bundle": 3,
  "num_bundles": 10,
  "seed": 30,
  "adaptive_alpha": true,
  "tau": 2.0,
  "mu": 10.0,
  "iteration_summaries": [
    {
      "iteration": 0,
      "mode": "initial",
      "bundles_total": 10,
      "bundles_solved": 10,
      "bundles_missing": 0,
      "elapsed_seconds": 6.786417182534933,
      "gurobi_threads_per_bundle": 1,
      "objective_min": 4383.547170751599,
      "objective_max": 7268.305220148281,
      "objective_mean": 5961.98989200642,
      "objective_std": 792.9712142944004,
      "start_utc": "2026-03-16T15:12:13.056360+00:00",
      "end_utc": "2026-03-16T15:12:19.842784+00:00",
      "gap": 646.8501758856137,
      "alpha": 100.0,
      "adaptive_alpha": true,
      "tau": 2.0,
      "mu": 10.0
    },
    {
      "iteration": 1,
      "mode": "augmented",
      "bundles_total": 10,
      "bundles_solved": 10,
      "bundles_missing": 0,
      "elapsed_seconds": 33.44524973630905,
      "gurobi_threads_per_bundle": 1,
      "objective_min": -2594997.161735356,
      "objective_max": 6855153.084276438,
      "objective_mean": 66695.64899107814,
      "objective_std": 3411414.9084529122,
      "start_utc": "2026-03-16T15:12:19.872953+00:00",
      "end_utc": "2026-03-16T15:12:53.318227+00:00",
      "gap": 314.9996289703371,
      "alpha": 100.0,
      "adaptive_alpha": true,
      "tau": 2.0,
      "mu": 10.0
    },
    {
      "iteration": 2,
      "mode": "augmented",
      "bundles_total": 10,
      "bundles_solved": 10,
      "bundles_missing": 0,
      "elapsed_seconds": 52.53006615489721,
      "gurobi_threads_per_bundle": 1,
      "objective_min": -1417540.1700591445,
      "objective_max": 3724011.9865906835,
      "objective_mean": 22542.64189029336,
      "objective_std": 1818351.5507461624,
      "start_utc": "2026-03-16T15:12:53.405502+00:00",
      "end_utc": "2026-03-16T15:13:45.935598+00:00",
      "gap": 164.09666297930025,
      "alpha": 100.0,
      "adaptive_alpha": true,
      "tau": 2.0,
      "mu": 10.0
    },
    {
      "iteration": 3,
      "mode": "augmented",
      "bundles_total": 10,
      "bundles_solved": 10,
      "bundles_missing": 0,
      "elapsed_seconds": 106.08357012271881,
      "gurobi_threads_per_bundle": 1,
      "objective_min": -800472.9457490444,
      "objective_max": 2077644.0471010208,
      "objective_mean": 10346.60248618722,
      "objective_std": 987670.871905512,
      "start_utc": "2026-03-16T15:13:46.033957+00:00",
      "end_utc": "2026-03-16T15:15:32.117544+00:00",
      "gap": 84.51859016845778,
      "alpha": 100.0,
      "adaptive_alpha": true,
      "tau": 2.0,
      "mu": 10.0
    },
    {
      "iteration": 4,
      "mode": "augmented",
      "bundles_total": 10,
      "bundles_solved": 10,
      "bundles_missing": 0,
      "elapsed_seconds": 17.33105583116412,
      "gurobi_threads_per_bundle": 1,
      "objective_min": -402988.9897044897,
      "objective_max": 1110114.7917631865,
      "objective_mean": 6912.220984631776,
      "objective_std": 517552.0545040912,
      "start_utc": "2026-03-16T15:15:32.216185+00:00",
      "end_utc": "2026-03-16T15:15:49.547260+00:00",
      "gap": 38.160771080768534,
      "alpha": 100.0,
      "adaptive_alpha": true,
      "tau": 2.0,
      "mu": 10.0
    },
    {
      "iteration": 5,
      "mode": "augmented",
      "bundles_total": 10,
      "bundles_solved": 10,
      "bundles_missing": 0,
      "elapsed_seconds": 40.15305932611227,
      "gurobi_threads_per_bundle": 1,
      "objective_min": -257675.4191120863,
      "objective_max": 667164.6427922845,
      "objective_mean": 6063.641535723209,
      "objective_std": 314778.7176960379,
      "start_utc": "2026-03-16T15:15:49.620128+00:00",
      "end_utc": "2026-03-16T15:16:29.773207+00:00",
      "gap": 23.468672173369477,
      "alpha": 100.0,
      "adaptive_alpha": true,
      "tau": 2.0,
      "mu": 10.0
    },
    {
      "iteration": 6,
      "mode": "augmented",
      "bundles_total": 10,
      "bundles_solved": 10,
      "bundles_missing": 0,
      "elapsed_seconds": 37.79380835220218,
      "gurobi_threads_per_bundle": 1,
      "objective_min": -144626.19528096914,
      "objective_max": 377728.4144999385,
      "objective_mean": 5728.7061400353905,
      "objective_std": 183254.95298478875,
      "start_utc": "2026-03-16T15:16:29.872614+00:00",
      "end_utc": "2026-03-16T15:17:07.666445+00:00",
      "gap": 18.17327752849879,
      "alpha": 100.0,
      "adaptive_alpha": true,
      "tau": 2.0,
      "mu": 10.0
    },
    {
      "iteration": 7,
      "mode": "augmented",
      "bundles_total": 10,
      "bundles_solved": 10,
      "bundles_missing": 0,
      "elapsed_seconds": 45.18981583788991,
      "gurobi_threads_per_bundle": 1,
      "objective_min": -51904.73714160919,
      "objective_max": 192130.79678416252,
      "objective_mean": 5582.575376719236,
      "objective_std": 84243.67640095229,
      "start_utc": "2026-03-16T15:17:07.762622+00:00",
      "end_utc": "2026-03-16T15:17:52.952455+00:00",
      "gap": 11.003741864921304,
      "alpha": 50.0,
      "adaptive_alpha": true,
      "tau": 2.0,
      "mu": 10.0
    },
    {
      "iteration": 8,
      "mode": "augmented",
      "bundles_total": 10,
      "bundles_solved": 10,
      "bundles_missing": 0,
      "elapsed_seconds": 41.15451746433973,
      "gurobi_threads_per_bundle": 1,
      "objective_min": -27845.213599085808,
      "objective_max": 67403.12893512845,
      "objective_mean": 5613.770805960894,
      "objective_std": 31091.39390619132,
      "start_utc": "2026-03-16T15:17:52.986923+00:00",
      "end_utc": "2026-03-16T15:18:34.141454+00:00",
      "gap": 13.327299948187548,
      "alpha": 50.0,
      "adaptive_alpha": true,
      "tau": 2.0,
      "mu": 10.0
    },
    {
      "iteration": 9,
      "mode": "augmented",
      "bundles_total": 10,
      "bundles_solved": 10,
      "bundles_missing": 0,
      "elapsed_seconds": 13.59092415869236,
      "gurobi_threads_per_bundle": 1,
      "objective_min": -23177.997402727604,
      "objective_max": 93085.57682546973,
      "objective_mean": 5628.504728066921,
      "objective_std": 38157.7754899758,
      "start_utc": "2026-03-16T15:18:34.175608+00:00",
      "end_utc": "2026-03-16T15:18:47.766597+00:00",
      "gap": 11.54347764864249,
      "alpha": 100.0,
      "adaptive_alpha": true,
      "tau": 2.0,
      "mu": 10.0
    },
    {
      "iteration": 10,
      "mode": "augmented",
      "bundles_total": 10,
      "bundles_solved": 10,
      "bundles_missing": 0,
      "elapsed_seconds": 16.773788526654243,
      "gurobi_threads_per_bundle": 1,
      "objective_min": -4434.49498039484,
      "objective_max": 15017.047788798809,
      "objective_mean": 5531.402150917053,
      "objective_std": 4394.153270161768,
      "start_utc": "2026-03-16T15:18:47.836496+00:00",
      "end_utc": "2026-03-16T15:19:04.610302+00:00",
      "gap": 8.313180277111616,
      "alpha": 100.0,
      "adaptive_alpha": true,
      "tau": 2.0,
      "mu": 10.0
    },
    {
      "iteration": 11,
      "mode": "augmented",
      "bundles_total": 10,
      "bundles_solved": 10,
      "bundles_missing": 0,
      "elapsed_seconds": 13.420582495629787,
      "gurobi_threads_per_bundle": 1,
      "objective_min": -39983.589972257614,
      "objective_max": 129386.86362427473,
      "objective_mean": 5627.821574723721,
      "objective_std": 51117.56000071187,
      "start_utc": "2026-03-16T15:19:04.643744+00:00",
      "end_utc": "2026-03-16T15:19:18.064341+00:00",
      "gap": 8.284161416404853,
      "alpha": 100.0,
      "adaptive_alpha": true,
      "tau": 2.0,
      "mu": 10.0
    },
    {
      "iteration": 12,
      "mode": "augmented",
      "bundles_total": 10,
      "bundles_solved": 10,
      "bundles_missing": 0,
      "elapsed_seconds": 22.91533839330077,
      "gurobi_threads_per_bundle": 1,
      "objective_min": -4599.137165188789,
      "objective_max": 15832.543378293514,
      "objective_mean": 5549.019191128015,
      "objective_std": 4598.969910778203,
      "start_utc": "2026-03-16T15:19:18.135029+00:00",
      "end_utc": "2026-03-16T15:19:41.050389+00:00",
      "gap": 8.142735985392445,
      "alpha": 200.0,
      "adaptive_alpha": true,
      "tau": 2.0,
      "mu": 10.0
    },
    {
      "iteration": 13,
      "mode": "augmented",
      "bundles_total": 10,
      "bundles_solved": 10,
      "bundles_missing": 0,
      "elapsed_seconds": 22.245260071009398,
      "gurobi_threads_per_bundle": 1,
      "objective_min": -40185.30253279209,
      "objective_max": 129527.1330024004,
      "objective_mean": 5548.104595315456,
      "objective_std": 51150.19166252127,
      "start_utc": "2026-03-16T15:19:41.104701+00:00",
      "end_utc": "2026-03-16T15:20:03.349981+00:00",
      "gap": 8.036049742065709,
      "alpha": 400.0,
      "adaptive_alpha": true,
      "tau": 2.0,
      "mu": 10.0
    },
    {
      "iteration": 14,
      "mode": "augmented",
      "bundles_total": 10,
      "bundles_solved": 10,
      "bundles_missing": 0,
      "elapsed_seconds": 16.622894510626793,
      "gurobi_threads_per_bundle": 1,
      "objective_min": -98123.50021600723,
      "objective_max": 50612.36887025833,
      "objective_mean": 5388.969339418411,
      "objective_std": 45093.48618621902,
      "start_utc": "2026-03-16T15:20:03.380425+00:00",
      "end_utc": "2026-03-16T15:20:20.003337+00:00",
      "gap": 8.009397873163001,
      "alpha": 800.0,
      "adaptive_alpha": true,
      "tau": 2.0,
      "mu": 10.0
    },
    {
      "iteration": 15,
      "mode": "augmented",
      "bundles_total": 10,
      "bundles_solved": 10,
      "bundles_missing": 0,
      "elapsed_seconds": 12.214753713458776,
      "gurobi_threads_per_bundle": 1,
      "objective_min": -131590.33964920044,
      "objective_max": 355797.37476205826,
      "objective_mean": 5227.800236415863,
      "objective_std": 146748.02190234984,
      "start_utc": "2026-03-16T15:20:20.071622+00:00",
      "end_utc": "2026-03-16T15:20:32.286389+00:00",
      "gap": 8.039614855213909,
      "alpha": 800.0,
      "adaptive_alpha": true,
      "tau": 2.0,
      "mu": 10.0
    },
    {
      "iteration": 16,
      "mode": "augmented",
      "bundles_total": 10,
      "bundles_solved": 10,
      "bundles_missing": 0,
      "elapsed_seconds": 10.763370402157307,
      "gurobi_threads_per_bundle": 1,
      "objective_min": -552487.274916172,
      "objective_max": 232610.2653260231,
      "objective_mean": 5389.0208371639255,
      "objective_std": 236769.2544737336,
      "start_utc": "2026-03-16T15:20:32.380533+00:00",
      "end_utc": "2026-03-16T15:20:43.143921+00:00",
      "gap": 8.020219084920615,
      "alpha": 800.0,
      "adaptive_alpha": true,
      "tau": 2.0,
      "mu": 10.0
    },
    {
      "iteration": 17,
      "mode": "augmented",
      "bundles_total": 10,
      "bundles_solved": 10,
      "bundles_missing": 0,
      "elapsed_seconds": 10.128293715417385,
      "gurobi_threads_per_bundle": 1,
      "objective_min": -131590.8643937111,
      "objective_max": 355814.3846321106,
      "objective_mean": 5228.113435268402,
      "objective_std": 146746.4686475828,
      "start_utc": "2026-03-16T15:20:43.173964+00:00",
      "end_utc": "2026-03-16T15:20:53.302272+00:00",
      "gap": 8.010098724110843,
      "alpha": 800.0,
      "adaptive_alpha": true,
      "tau": 2.0,
      "mu": 10.0
    },
    {
      "iteration": 18,
      "mode": "augmented",
      "bundles_total": 10,
      "bundles_solved": 10,
      "bundles_missing": 0,
      "elapsed_seconds": 12.086344603449106,
      "gurobi_threads_per_bundle": 1,
      "objective_min": -552479.026248455,
      "objective_max": 232610.1304488182,
      "objective_mean": 5205.582828998566,
      "objective_std": 237030.30568912605,
      "start_utc": "2026-03-16T15:20:53.334817+00:00",
      "end_utc": "2026-03-16T15:21:05.421176+00:00",
      "gap": 9.188143124410146,
      "alpha": 400.0,
      "adaptive_alpha": true,
      "tau": 2.0,
      "mu": 10.0
    },
    {
      "iteration": 19,
      "mode": "augmented",
      "bundles_total": 10,
      "bundles_solved": 10,
      "bundles_missing": 0,
      "elapsed_seconds": 20.364401385188103,
      "gurobi_threads_per_bundle": 1,
      "objective_min": -192740.7624759674,
      "objective_max": 475499.4578592777,
      "objective_mean": 5570.347673392296,
      "objective_std": 204997.80926565378,
      "start_utc": "2026-03-16T15:21:05.464573+00:00",
      "end_utc": "2026-03-16T15:21:25.828990+00:00",
      "gap": 9.186950656882145,
      "alpha": 200.0,
      "adaptive_alpha": true,
      "tau": 2.0,
      "mu": 10.0
    },
    {
      "iteration": 20,
      "mode": "augmented",
      "bundles_total": 10,
      "bundles_solved": 10,
      "bundles_missing": 0,
      "elapsed_seconds": 25.34191456064582,
      "gurobi_threads_per_bundle": 1,
      "objective_min": -115036.35301542282,
      "objective_max": 70222.60976743698,
      "objective_mean": 5582.750074744225,
      "objective_std": 45213.3245548366,
      "start_utc": "2026-03-16T15:21:25.842541+00:00",
      "end_utc": "2026-03-16T15:21:51.184470+00:00",
      "gap": 9.191467790158047,
      "alpha": 200.0,
      "adaptive_alpha": true,
      "tau": 2.0,
      "mu": 10.0
    },
    {
      "iteration": 21,
      "mode": "augmented",
      "bundles_total": 10,
      "bundles_solved": 10,
      "bundles_missing": 0,
      "elapsed_seconds": 21.762752305716276,
      "gurobi_threads_per_bundle": 1,
      "objective_min": -55556.38702297211,
      "objective_max": 140372.76424646378,
      "objective_mean": 5549.1765578508375,
      "objective_std": 64331.07455208097,
      "start_utc": "2026-03-16T15:21:51.254549+00:00",
      "end_utc": "2026-03-16T15:22:13.017314+00:00",
      "gap": 8.979577181171207,
      "alpha": 400.0,
      "adaptive_alpha": true,
      "tau": 2.0,
      "mu": 10.0
    },
    {
      "iteration": 22,
      "mode": "augmented",
      "bundles_total": 10,
      "bundles_solved": 10,
      "bundles_missing": 0,
      "elapsed_seconds": 21.896403938531876,
      "gurobi_threads_per_bundle": 1,
      "objective_min": -97868.85601615906,
      "objective_max": 50593.91022109985,
      "objective_mean": 5367.742048859596,
      "objective_std": 45173.18993440405,
      "start_utc": "2026-03-16T15:22:13.092662+00:00",
      "end_utc": "2026-03-16T15:22:34.989085+00:00",
      "gap": 8.053826307772745,
      "alpha": 200.0,
      "adaptive_alpha": true,
      "tau": 2.0,
      "mu": 10.0
    },
    {
      "iteration": 23,
      "mode": "augmented",
      "bundles_total": 10,
      "bundles_solved": 10,
      "bundles_missing": 0,
      "elapsed_seconds": 29.994253627955914,
      "gurobi_threads_per_bundle": 1,
      "objective_min": -130976.9322925806,
      "objective_max": 357435.53090143204,
      "objective_mean": 5707.665127670765,
      "objective_std": 147051.21016115817,
      "start_utc": "2026-03-16T15:22:35.019808+00:00",
      "end_utc": "2026-03-16T15:23:05.014080+00:00",
      "gap": 8.161727356128647,
      "alpha": 200.0,
      "adaptive_alpha": true,
      "tau": 2.0,
      "mu": 10.0
    },
    {
      "iteration": 24,
      "mode": "augmented",
      "bundles_total": 10,
      "bundles_solved": 10,
      "bundles_missing": 0,
      "elapsed_seconds": 23.002714697271585,
      "gurobi_threads_per_bundle": 1,
      "objective_min": -40101.9210139513,
      "objective_max": 129577.76959359646,
      "objective_mean": 5548.160568499565,
      "objective_std": 51118.28696944957,
      "start_utc": "2026-03-16T15:23:05.053740+00:00",
      "end_utc": "2026-03-16T15:23:28.056472+00:00",
      "gap": 8.086317747821644,
      "alpha": 200.0,
      "adaptive_alpha": true,
      "tau": 2.0,
      "mu": 10.0
    },
    {
      "iteration": 25,
      "mode": "augmented",
      "bundles_total": 10,
      "bundles_solved": 10,
      "bundles_missing": 0,
      "elapsed_seconds": 22.742705792188644,
      "gurobi_threads_per_bundle": 1,
      "objective_min": -97595.68006241322,
      "objective_max": 50854.46178150177,
      "objective_mean": 5548.954227042198,
      "objective_std": 45003.68972456084,
      "start_utc": "2026-03-16T15:23:28.134012+00:00",
      "end_utc": "2026-03-16T15:23:50.876734+00:00",
      "gap": 8.051607738956283,
      "alpha": 200.0,
      "adaptive_alpha": true,
      "tau": 2.0,
      "mu": 10.0
    },
    {
      "iteration": 26,
      "mode": "augmented",
      "bundles_total": 10,
      "bundles_solved": 10,
      "bundles_missing": 0,
      "elapsed_seconds": 22.268288873136044,
      "gurobi_threads_per_bundle": 1,
      "objective_min": -40168.87164795399,
      "objective_max": 129614.62440431118,
      "objective_mean": 5548.081431078911,
      "objective_std": 51150.104168207734,
      "start_utc": "2026-03-16T15:23:50.951006+00:00",
      "end_utc": "2026-03-16T15:24:13.219311+00:00",
      "gap": 8.026291325169652,
      "alpha": 400.0,
      "adaptive_alpha": true,
      "tau": 2.0,
      "mu": 10.0
    },
    {
      "iteration": 27,
      "mode": "augmented",
      "bundles_total": 10,
      "bundles_solved": 10,
      "bundles_missing": 0,
      "elapsed_seconds": 21.38728642091155,
      "gurobi_threads_per_bundle": 1,
      "objective_min": -98077.9635977745,
      "objective_max": 50621.01329040527,
      "objective_mean": 5388.944548153877,
      "objective_std": 45096.62907233652,
      "start_utc": "2026-03-16T15:24:13.316721+00:00",
      "end_utc": "2026-03-16T15:24:34.704026+00:00",
      "gap": 8.007513065286439,
      "alpha": 800.0,
      "adaptive_alpha": true,
      "tau": 2.0,
      "mu": 10.0
    },
    {
      "iteration": 28,
      "mode": "augmented",
      "bundles_total": 10,
      "bundles_solved": 10,
      "bundles_missing": 0,
      "elapsed_seconds": 23.074168033897877,
      "gurobi_threads_per_bundle": 1,
      "objective_min": -131586.6957039833,
      "objective_max": 355821.94049453735,
      "objective_mean": 5228.0742275238035,
      "objective_std": 146746.73243907964,
      "start_utc": "2026-03-16T15:24:34.733177+00:00",
      "end_utc": "2026-03-16T15:24:57.807363+00:00",
      "gap": 8.001722556884197,
      "alpha": 1600.0,
      "adaptive_alpha": true,
      "tau": 2.0,
      "mu": 10.0
    },
    {
      "iteration": 29,
      "mode": "augmented",
      "bundles_total": 10,
      "bundles_solved": 10,
      "bundles_missing": 0,
      "elapsed_seconds": 14.480570118874311,
      "gurobi_threads_per_bundle": 1,
      "objective_min": -554474.2412424088,
      "objective_max": 231811.5502500534,
      "objective_mean": 4748.944047164917,
      "objective_std": 237209.9505282834,
      "start_utc": "2026-03-16T15:24:57.880008+00:00",
      "end_utc": "2026-03-16T15:25:12.360597+00:00",
      "gap": 8.000862671696304,
      "alpha": 1600.0,
      "adaptive_alpha": true,
      "tau": 2.0,
      "mu": 10.0
    },
    {
      "iteration": 30,
      "mode": "augmented",
      "bundles_total": 10,
      "bundles_solved": 10,
      "bundles_missing": 0,
      "elapsed_seconds": 12.086840655654669,
      "gurobi_threads_per_bundle": 1,
      "objective_min": -495590.3193912506,
      "objective_max": 1264620.009147644,
      "objective_mean": 5227.660015106201,
      "objective_std": 530278.7806458113,
      "start_utc": "2026-03-16T15:25:12.410507+00:00",
      "end_utc": "2026-03-16T15:25:24.497364+00:00",
      "gap": 8.031390851340511,
      "alpha": 1600.0,
      "adaptive_alpha": true,
      "tau": 2.0,
      "mu": 10.0
    },
    {
      "iteration": 31,
      "mode": "augmented",
      "bundles_total": 10,
      "bundles_solved": 10,
      "bundles_missing": 0,
      "elapsed_seconds": 19.53952869772911,
      "gurobi_threads_per_bundle": 1,
      "objective_min": -554262.2242746353,
      "objective_max": 231887.17460727692,
      "objective_mean": 4749.022759246826,
      "objective_std": 237095.780022247,
      "start_utc": "2026-03-16T15:25:24.550272+00:00",
      "end_utc": "2026-03-16T15:25:44.089815+00:00",
      "gap": 8.016049786719607,
      "alpha": 3200.0,
      "adaptive_alpha": true,
      "tau": 2.0,
      "mu": 10.0
    },
    {
      "iteration": 32,
      "mode": "augmented",
      "bundles_total": 10,
      "bundles_solved": 10,
      "bundles_missing": 0,
      "elapsed_seconds": 11.857853200286627,
      "gurobi_threads_per_bundle": 1,
      "objective_min": -497153.3635368347,
      "objective_max": 1260718.9849681854,
      "objective_mean": 3948.084989738464,
      "objective_std": 529442.2846757119,
      "start_utc": "2026-03-16T15:25:44.183046+00:00",
      "end_utc": "2026-03-16T15:25:56.040917+00:00",
      "gap": 8.004434050502475,
      "alpha": 6400.0,
      "adaptive_alpha": true,
      "tau": 2.0,
      "mu": 10.0
    },
    {
      "iteration": 33,
      "mode": "augmented",
      "bundles_total": 10,
      "bundles_solved": 10,
      "bundles_missing": 0,
      "elapsed_seconds": 10.25260815024376,
      "gurobi_threads_per_bundle": 1,
      "objective_min": -2380047.1599998474,
      "objective_max": 956627.3951225281,
      "objective_mean": 2188.9453762054445,
      "objective_std": 1006072.2199176159,
      "start_utc": "2026-03-16T15:25:56.074048+00:00",
      "end_utc": "2026-03-16T15:26:06.326672+00:00",
      "gap": 8.00156341779308,
      "alpha": 12800.0,
      "adaptive_alpha": true,
      "tau": 2.0,
      "mu": 10.0
    },
    {
      "iteration": 34,
      "mode": "augmented",
      "bundles_total": 10,
      "bundles_solved": 10,
      "bundles_missing": 0,
      "elapsed_seconds": 11.428791403770447,
      "gurobi_threads_per_bundle": 1,
      "objective_min": -1959589.354751587,
      "objective_max": 4879814.1876297,
      "objective_mean": -1172.0354202270507,
      "objective_std": 2060062.158646058,
      "start_utc": "2026-03-16T15:26:06.359978+00:00",
      "end_utc": "2026-03-16T15:26:17.788785+00:00",
      "gap": 8.004438960214525,
      "alpha": 12800.0,
      "adaptive_alpha": true,
      "tau": 2.0,
      "mu": 10.0
    },
    {
      "iteration": 35,
      "mode": "augmented",
      "bundles_total": 10,
      "bundles_solved": 10,
      "bundles_missing": 0,
      "elapsed_seconds": 12.832680251449347,
      "gurobi_threads_per_bundle": 1,
      "objective_min": -9650458.278297424,
      "objective_max": 3868508.4233398438,
      "objective_mean": 2188.9630348205565,
      "objective_std": 4074559.3220572947,
      "start_utc": "2026-03-16T15:26:17.841716+00:00",
      "end_utc": "2026-03-16T15:26:30.674413+00:00",
      "gap": 8.002544076361449,
      "alpha": 25600.0,
      "adaptive_alpha": true,
      "tau": 2.0,
      "mu": 10.0
    },
    {
      "iteration": 36,
      "mode": "augmented",
      "bundles_total": 10,
      "bundles_solved": 10,
      "bundles_missing": 0,
      "elapsed_seconds": 14.463878020644188,
      "gurobi_threads_per_bundle": 1,
      "objective_min": -1972531.518081665,
      "objective_max": 4848012.285995483,
      "objective_mean": -11411.922485351562,
      "objective_std": 2053002.922215419,
      "start_utc": "2026-03-16T15:26:30.727434+00:00",
      "end_utc": "2026-03-16T15:26:45.191329+00:00",
      "gap": 8.000685984525763,
      "alpha": 25600.0,
      "adaptive_alpha": true,
      "tau": 2.0,
      "mu": 10.0
    },
    {
      "iteration": 37,
      "mode": "augmented",
      "bundles_total": 10,
      "bundles_solved": 10,
      "bundles_missing": 0,
      "elapsed_seconds": 13.951547171920538,
      "gurobi_threads_per_bundle": 1,
      "objective_min": -24191001.446853638,
      "objective_max": 9691421.082336426,
      "objective_mean": 2095.486360168457,
      "objective_std": 10211335.457604475,
      "start_utc": "2026-03-16T15:26:45.246795+00:00",
      "end_utc": "2026-03-16T15:26:59.198359+00:00",
      "gap": 8.084409847383538,
      "alpha": 12800.0,
      "adaptive_alpha": true,
      "tau": 2.0,
      "mu": 10.0
    },
    {
      "iteration": 38,
      "mode": "augmented",
      "bundles_total": 10,
      "bundles_solved": 10,
      "bundles_missing": 0,
      "elapsed_seconds": 13.553620651364326,
      "gurobi_threads_per_bundle": 1,
      "objective_min": -1925316.703781128,
      "objective_max": 4874026.75995636,
      "objective_mean": -1134.8320388793945,
      "objective_std": 2055618.8174861073,
      "start_utc": "2026-03-16T15:26:59.270043+00:00",
      "end_utc": "2026-03-16T15:27:12.823680+00:00",
      "gap": 8.082606302151895,
      "alpha": 12800.0,
      "adaptive_alpha": true,
      "tau": 2.0,
      "mu": 10.0
    },
    {
      "iteration": 39,
      "mode": "augmented",
      "bundles_total": 10,
      "bundles_solved": 10,
      "bundles_missing": 0,
      "elapsed_seconds": 14.680515132844448,
      "gurobi_threads_per_bundle": 1,
      "objective_min": -9653173.863960266,
      "objective_max": 3885458.374420166,
      "objective_mean": 2198.2723907470704,
      "objective_std": 4076742.343727411,
      "start_utc": "2026-03-16T15:27:12.891562+00:00",
      "end_utc": "2026-03-16T15:27:27.572094+00:00",
      "gap": 8.04403318825608,
      "alpha": 12800.0,
      "adaptive_alpha": true,
      "tau": 2.0,
      "mu": 10.0
    },
    {
      "iteration": 40,
      "mode": "augmented",
      "bundles_total": 10,
      "bundles_solved": 10,
      "bundles_missing": 0,
      "elapsed_seconds": 11.154840368777514,
      "gurobi_threads_per_bundle": 1,
      "objective_min": -1951490.3162841797,
      "objective_max": 4878703.832870483,
      "objective_mean": -1169.8029891967774,
      "objective_std": 2059038.7518590034,
      "start_utc": "2026-03-16T15:27:27.622750+00:00",
      "end_utc": "2026-03-16T15:27:38.777607+00:00",
      "gap": 8.027772581254672,
      "alpha": 12800.0,
      "adaptive_alpha": true,
      "tau": 2.0,
      "mu": 10.0
    },
    {
      "iteration": 41,
      "mode": "augmented",
      "bundles_total": 10,
      "bundles_solved": 10,
      "bundles_missing": 0,
      "elapsed_seconds": 12.200014617294073,
      "gurobi_threads_per_bundle": 1,
      "objective_min": -9650788.724655151,
      "objective_max": 3872404.6593933105,
      "objective_mean": 2188.4721145629883,
      "objective_std": 4075006.983049485,
      "start_utc": "2026-03-16T15:27:38.805332+00:00",
      "end_utc": "2026-03-16T15:27:51.005363+00:00",
      "gap": 8.021738919598313,
      "alpha": 12800.0,
      "adaptive_alpha": true,
      "tau": 2.0,
      "mu": 10.0
    },
    {
      "iteration": 42,
      "mode": "augmented",
      "bundles_total": 10,
      "bundles_solved": 10,
      "bundles_missing": 0,
      "elapsed_seconds": 10.67959002405405,
      "gurobi_threads_per_bundle": 1,
      "objective_min": -1960491.8363723755,
      "objective_max": 4880366.164260864,
      "objective_mean": -1171.5427932739258,
      "objective_std": 2060238.4206389543,
      "start_utc": "2026-03-16T15:27:51.037679+00:00",
      "end_utc": "2026-03-16T15:28:01.717283+00:00",
      "gap": 8.011432913742508,
      "alpha": 12800.0,
      "adaptive_alpha": true,
      "tau": 2.0,
      "mu": 10.0
    },
    {
      "iteration": 43,
      "mode": "augmented",
      "bundles_total": 10,
      "bundles_solved": 10,
      "bundles_missing": 0,
      "elapsed_seconds": 11.895259317010641,
      "gurobi_threads_per_bundle": 1,
      "objective_min": -9649988.094551086,
      "objective_max": 3867899.0241851807,
      "objective_mean": 2189.041566467285,
      "objective_std": 4074404.7627433348,
      "start_utc": "2026-03-16T15:28:01.759928+00:00",
      "end_utc": "2026-03-16T15:28:13.655203+00:00",
      "gap": 8.005972099488744,
      "alpha": 12800.0,
      "adaptive_alpha": true,
      "tau": 2.0,
      "mu": 10.0
    },
    {
      "iteration": 44,
      "mode": "augmented",
      "bundles_total": 10,
      "bundles_solved": 10,
      "bundles_missing": 0,
      "elapsed_seconds": 12.710829440504313,
      "gurobi_threads_per_bundle": 1,
      "objective_min": -1960190.7655181885,
      "objective_max": 4880297.043174744,
      "objective_mean": -1171.9051605224608,
      "objective_std": 2060207.802634127,
      "start_utc": "2026-03-16T15:28:13.704073+00:00",
      "end_utc": "2026-03-16T15:28:26.414916+00:00",
      "gap": 8.003286012635972,
      "alpha": 12800.0,
      "adaptive_alpha": true,
      "tau": 2.0,
      "mu": 10.0
    },
    {
      "iteration": 45,
      "mode": "augmented",
      "bundles_total": 10,
      "bundles_solved": 10,
      "bundles_missing": 0,
      "elapsed_seconds": 12.394811414182186,
      "gurobi_threads_per_bundle": 1,
      "objective_min": -9650000.584098816,
      "objective_max": 3868052.8187026978,
      "objective_mean": 2188.9434814453125,
      "objective_std": 4074423.3651033784,
      "start_utc": "2026-03-16T15:28:26.486255+00:00",
      "end_utc": "2026-03-16T15:28:38.881084+00:00",
      "gap": 8.002693900444871,
      "alpha": 12800.0,
      "adaptive_alpha": true,
      "tau": 2.0,
      "mu": 10.0
    },
    {
      "iteration": 46,
      "mode": "augmented",
      "bundles_total": 10,
      "bundles_solved": 10,
      "bundles_missing": 0,
      "elapsed_seconds": 11.041258618235588,
      "gurobi_threads_per_bundle": 1,
      "objective_min": -1960112.3817520142,
      "objective_max": 4880301.113021851,
      "objective_mean": -1171.9218505859376,
      "objective_std": 2060193.0281177426,
      "start_utc": "2026-03-16T15:28:38.948303+00:00",
      "end_utc": "2026-03-16T15:28:49.989581+00:00",
      "gap": 8.001286843067978,
      "alpha": 12800.0,
      "adaptive_alpha": true,
      "tau": 2.0,
      "mu": 10.0
    },
    {
      "iteration": 47,
      "mode": "augmented",
      "bundles_total": 10,
      "bundles_solved": 10,
      "bundles_missing": 0,
      "elapsed_seconds": 11.195203345268965,
      "gurobi_threads_per_bundle": 1,
      "objective_min": -9649995.290794373,
      "objective_max": 3868093.3238754272,
      "objective_mean": 2188.945623779297,
      "objective_std": 4074426.4380139,
      "start_utc": "2026-03-16T15:28:50.056781+00:00",
      "end_utc": "2026-03-16T15:29:01.252002+00:00",
      "gap": 8.000827133633537,
      "alpha": 25600.0,
      "adaptive_alpha": true,
      "tau": 2.0,
      "mu": 10.0
    },
    {
      "iteration": 48,
      "mode": "augmented",
      "bundles_total": 10,
      "bundles_solved": 10,
      "bundles_missing": 0,
      "elapsed_seconds": 13.325361285358667,
      "gurobi_threads_per_bundle": 1,
      "objective_min": -1972895.7552490234,
      "objective_max": 4848303.872009277,
      "objective_mean": -11411.92439880371,
      "objective_std": 2053079.5451191037,
      "start_utc": "2026-03-16T15:29:01.302941+00:00",
      "end_utc": "2026-03-16T15:29:14.628356+00:00",
      "gap": 8.000220525123877,
      "alpha": 51200.0,
      "adaptive_alpha": true,
      "tau": 2.0,
      "mu": 10.0
    },
    {
      "iteration": 49,
      "mode": "augmented",
      "bundles_total": 10,
      "bundles_solved": 10,
      "bundles_missing": 0,
      "elapsed_seconds": 11.112152572721243,
      "gurobi_threads_per_bundle": 1,
      "objective_min": -24255220.675842285,
      "objective_max": 9666499.538482666,
      "objective_mean": -18333.840838623048,
      "objective_std": 10225749.05272071,
      "start_utc": "2026-03-16T15:29:14.658162+00:00",
      "end_utc": "2026-03-16T15:29:25.770328+00:00",
      "gap": 8.040753568278522,
      "alpha": 25600.0,
      "adaptive_alpha": true,
      "tau": 2.0,
      "mu": 10.0
    },
    {
      "iteration": 50,
      "mode": "augmented",
      "bundles_total": 10,
      "bundles_solved": 10,
      "bundles_missing": 0,
      "elapsed_seconds": 12.672466352581978,
      "gurobi_threads_per_bundle": 1,
      "objective_min": -13583652.404876709,
      "objective_max": 33969909.50016785,
      "objective_mean": 9026.793536376954,
      "objective_std": 14333884.146177046,
      "start_utc": "2026-03-16T15:29:25.795455+00:00",
      "end_utc": "2026-03-16T15:29:38.467938+00:00",
      "gap": 8.119463676275373,
      "alpha": 12800.0,
      "adaptive_alpha": true,
      "tau": 2.0,
      "mu": 10.0
    }
  ]
}